pulsejet-0.1.5.dist-info/METADATA
pulsejet-0.1.5.dist-info/WHEEL
pulsejet-0.1.5.dist-info/license_files/LICENSE
pulsejet.libs/libgfortran-91cc3cb1.so.3
pulsejet.libs/libblas-357956a1.so.3
pulsejet.libs/libk5crypto-b1f99d5c.so.3
pulsejet.libs/libcom_err-2abe824b.so.2
pulsejet.libs/libquadmath-96973f99.so.0
pulsejet.libs/libkrb5-fcafa220.so.3
pulsejet.libs/libpcre-9513aab5.so.1
pulsejet.libs/libgomp-a34b3233.so.1
pulsejet.libs/libssl-cd1d6220.so.10
pulsejet.libs/libselinux-0922c95c.so.1
pulsejet.libs/libcrypto-d3570994.so.10
pulsejet.libs/liblapack-1ad85175.so.3
pulsejet.libs/libgssapi_krb5-497db0c6.so.2
pulsejet.libs/libkrb5support-d0bcff84.so.0
pulsejet.libs/libkeyutils-dfe70bd6.so.1
pulsejet/client/parallel_processor.py
pulsejet/client/async_client.py
pulsejet/client/pj_local.py
pulsejet/client/async_pj_base.py
pulsejet/client/async_pj_local.py
pulsejet/client/__init__.py
pulsejet/client/connections.py
pulsejet/client/async_pj_remote.py
pulsejet/client/grpc_multi_inserter.py
pulsejet/client/pj_remote.py
pulsejet/client/pj_base.py
pulsejet/client/client.py
pulsejet/__init__.py
pulsejet/gen/common_pb2.py
pulsejet/gen/search_pb2.pyi
pulsejet/gen/embeds_pb2.pyi
pulsejet/gen/embeds_service_pb2.py
pulsejet/gen/embeds_pb2_grpc.py
pulsejet/gen/embeds_pb2.py
pulsejet/gen/.gitkeep
pulsejet/gen/search_pb2_grpc.py
pulsejet/gen/embeds_service_pb2.pyi
pulsejet/gen/collections_service_pb2.pyi
pulsejet/gen/collections_service_pb2.py
pulsejet/gen/collections_pb2.py
pulsejet/gen/search_service_pb2.py
pulsejet/gen/collections_service_pb2_grpc.py
pulsejet/gen/common_pb2_grpc.py
pulsejet/gen/__init__.py
pulsejet/gen/collections_pb2_grpc.py
pulsejet/gen/embeds_service_pb2_grpc.py
pulsejet/gen/collections_pb2.pyi
pulsejet/gen/search_service_pb2_grpc.py
pulsejet/gen/search_pb2.py
pulsejet/gen/search_service_pb2.pyi
pulsejet/gen/common_pb2.pyi
pulsejet/pulsejet.cpython-312-x86_64-linux-gnu.so
pulsejet-0.1.5.dist-info/RECORD
