Metadata-Version: 2.3
Name: pulsejet
Version: 0.1.5
Classifier: Programming Language :: Rust
Classifier: Programming Language :: Python :: Implementation :: CPython
Classifier: Programming Language :: Python :: Implementation :: PyPy
Requires-Dist: grpcio >=1.64
License-File: LICENSE
Summary: PulsejetDB - Vector database for local and cloud development
Requires-Python: >=3.8
Project-URL: homepage, https://jetengine.tech
Project-URL: documentation, https://docs.pulsejet.jetengine.tech
